LICENSE
MANIFEST.in
README.rst
requirements.txt
setup.py
csv2sql/__init__.py
csv2sql/__main__.py
csv2sql/main.py
csv2sql/meta.py
csv2sql.egg-info/PKG-INFO
csv2sql.egg-info/SOURCES.txt
csv2sql.egg-info/dependency_links.txt
csv2sql.egg-info/entry_points.txt
csv2sql.egg-info/requires.txt
csv2sql.egg-info/top_level.txt
csv2sql/core/__init__.py
csv2sql/core/error.py
csv2sql/core/my_logging.py
csv2sql/core/prefetching.py
csv2sql/core/type_inference.py
csv2sql/queryengines/__init__.py
csv2sql/queryengines/psql.py
tests/test_main.py
tests/core/__init__.py
tests/core/test_my_logger.py
tests/core/test_prefetching.py
tests/core/test_type_inference.py