Metadata-Version: 1.1
Name: csv2sql
Version: 0.4.0
Summary: Convert CSV data into SQL.
Home-page: https://github.com/ymoch/csv2sql
Author: Yu Mochizuki
Author-email: ymoch.dev@gmail.com
License: UNKNOWN
Platform: UNKNOWN
Classifier: Development Status :: 3 - Alpha
Classifier: Environment :: Console
Classifier: Intended Audience :: Developers
Classifier: Intended Audience :: Information Technology
Classifier: License :: OSI Approved :: MIT License
Classifier: Programming Language :: Python
Classifier: Programming Language :: Python :: 2.7
Classifier: Programming Language :: Python :: 3.3
Classifier: Programming Language :: Python :: 3.4
Classifier: Programming Language :: Python :: 3.5
Classifier: Programming Language :: SQL
Classifier: Topic :: Software Development :: Code Generators
Classifier: Topic :: Utilities
